iranetf/__init__.py
iranetf/dataset.csv
iranetf/dataset.py
iranetf/rahavard365.py
iranetf/sites/__init__.py
iranetf/sites/_lib.py
iranetf/sites/_mabnadp.py
iranetf/sites/_rayanhamafza.py
iranetf/sites/_tadbirpardaz.py
iranetf-1.0.0.dist-info/WHEEL
iranetf-1.0.0.dist-info/METADATA
iranetf-1.0.0.dist-info/RECORD
