Metadata-Version: 2.3
Name: iranetf
Version: 1.0.0
Summary: a library to fetch data from ETF websites active TSE
Author: 5j9
Author-email: 5j9 <5j9@users.noreply.github.com>
Classifier: Programming Language :: Python :: 3
Classifier: License :: OSI Approved :: GNU General Public License v3 or later (GPLv3+)
Classifier: Operating System :: OS Independent
Requires-Dist: aiohttp[speedups]
Requires-Dist: aiohutils>=0.22.3
Requires-Dist: jdatetime>=4.1.0
Requires-Dist: pandas[pyarrow]>=2.2.1
Requires-Dist: tsetmc>=2.0.2
Requires-Dist: fipiran>=1.0.2
Requires-Python: >=3.13
Project-URL: Homepage, https://github.com/5j9/iranetf
